ccanvas/__init__.py
ccanvas/__main__.py
ccanvas/config.py
ccanvas/core/__init__.py
ccanvas/core/canvas.py
ccanvas/core/line_builder.py
ccanvas/interface/__init__.py
ccanvas/interface/cli.py
tests/test_placeholder.py
ccanvas-1.5.1.dist-info/LICENSE
ccanvas-1.5.1.dist-info/METADATA
ccanvas-1.5.1.dist-info/WHEEL
ccanvas-1.5.1.dist-info/top_level.txt
ccanvas-1.5.1.dist-info/RECORD
