Metadata-Version: 2.1
Name: ccanvas
Version: 1.5.1
Summary: Matplotlib-based canvas that allows line drawing and coordinate retrieval
Author-email: Paulo Sanchez <dev.szblzpaulo@gmail.com>
Maintainer-email: Paulo Sanchez <dev.szblzpaulo@gmail.com>
License: GNU AFFERO GENERAL PUBLIC LICENSE
Project-URL: Homepage, https://github.com/erlete/coordinate-canvas
Project-URL: Bug Tracker, https://github.com/erlete/coordinate-canvas/issues
Classifier: Development Status :: 5 - Production/Stable
Classifier: Intended Audience :: Developers
Classifier: Intended Audience :: Education
Classifier: Intended Audience :: Science/Research
Classifier: License :: OSI Approved :: GNU General Public License v3 (GPLv3)
Classifier: Operating System :: OS Independent
Classifier: Programming Language :: Python :: 3.8
Classifier: Programming Language :: Python :: 3.9
Classifier: Programming Language :: Python :: 3.10
Classifier: Programming Language :: Python :: 3.11
Classifier: Typing :: Typed
Requires-Python: >=3.11.6
License-File: LICENSE
Requires-Dist: bidimensional >=1.9.1
Requires-Dist: click >=8.1.7
Requires-Dist: colorama >=0.4.6
Requires-Dist: matplotlib >=3.8.2
Provides-Extra: test
Requires-Dist: pytest ==7.4.3 ; extra == 'test'
Requires-Dist: pytest-cov ==4.1.0 ; extra == 'test'
Requires-Dist: pytest-html ==4.1.1 ; extra == 'test'
Requires-Dist: pycodestyle ==2.11.1 ; extra == 'test'
Requires-Dist: pydocstyle ==6.3.0 ; extra == 'test'
Requires-Dist: mypy ==1.7.0 ; extra == 'test'
Requires-Dist: flake8 ==6.1.0 ; extra == 'test'
